currentsapi/__init__.py
currentsapi/authentication.py
currentsapi/client.py
currentsapi/constants.py
currentsapi_py/__init__.py
currentsapi_py/authentication.py
currentsapi_py/client.py
currentsapi_py/constants.py
currentsapi-0.0.2.dist-info/LICENSE.txt
currentsapi-0.0.2.dist-info/METADATA
currentsapi-0.0.2.dist-info/WHEEL
currentsapi-0.0.2.dist-info/top_level.txt
currentsapi-0.0.2.dist-info/RECORD
