Metadata-Version: 2.1
Name: currentsapi
Version: 0.0.2
Summary: Official Python client for the Currents API
Home-page: https://github.com/currentsapi-dev/currentsapi-python
Author: Zhi Rui Tam
Author-email: ray@currentsapi.services
License: MIT
Download-URL: https://github.com/currentsapi-dev/currentsapi-python/archive/master.zip
Keywords: currentsapi,news,wrapper
Platform: UNKNOWN
Classifier: Development Status :: 5 - Production/Stable
Classifier: Intended Audience :: Developers
Classifier: Intended Audience :: Financial and Insurance Industry
Classifier: Intended Audience :: Information Technology
Classifier: Topic :: Software Development :: Libraries :: Python Modules
Classifier: License :: OSI Approved :: MIT License
Classifier: Programming Language :: Python :: 2
Classifier: Programming Language :: Python :: 2.6
Classifier: Programming Language :: Python :: 2.7
Classifier: Programming Language :: Python :: 3
Classifier: Programming Language :: Python :: 3.3
Classifier: Programming Language :: Python :: 3.4
Classifier: Programming Language :: Python :: 3.5
Requires-Dist: requests (==2.21.0)
Requires-Dist: python-dateutil (==2.8.0)
